fog_of_world_data_parser/__init__.py
fog_of_world_data_parser/parser.py
fog_of_world_data_parser-0.1.5.dist-info/METADATA
fog_of_world_data_parser-0.1.5.dist-info/WHEEL
fog_of_world_data_parser-0.1.5.dist-info/licenses/LICENSE
fog_of_world_data_parser-0.1.5.dist-info/RECORD
