Metadata-Version: 2.4
Name: fog-of-world-data-parser
Version: 0.1.5
Summary: A data parser for the internal syncing data format used by Fog of World
Project-URL: Homepage, https://github.com/tslmy/Fog-of-World-Data-Parser
Project-URL: Repository, https://github.com/tslmy/Fog-of-World-Data-Parser
Project-URL: Issues, https://github.com/tslmy/Fog-of-World-Data-Parser/issues
Author-email: "Zed (Zijun) Chen" <zed@zijun.dev>, Ming <pypi-fogdp@myli.page>
License-File: LICENSE
Keywords: data-parser,fog-of-world,visualization
Classifier: Development Status :: 3 - Alpha
Classifier: Intended Audience :: Developers
Classifier: Programming Language :: Python :: 3
Classifier: Programming Language :: Python :: 3.8
Classifier: Programming Language :: Python :: 3.9
Classifier: Programming Language :: Python :: 3.10
Classifier: Programming Language :: Python :: 3.11
Classifier: Programming Language :: Python :: 3.12
Requires-Python: >=3.13
